foldindent.py
foldindent-0.5.0.dist-info/METADATA
foldindent-0.5.0.dist-info/WHEEL
foldindent-0.5.0.dist-info/entry_points.txt
foldindent-0.5.0.dist-info/licenses/COPYING.WTFPL
foldindent-0.5.0.dist-info/RECORD
