Metadata-Version: 2.4
Name: foldindent
Version: 0.5.0
Summary: foldindent - indented text viewer with folding
Project-URL: Homepage, https://gitlab.com/hydrargyrum/foldindent
Author-email: Hg <dev@indigo.re>
License-Expression: WTFPL
License-File: COPYING.WTFPL
Keywords: indentation,text
Requires-Python: >=3
Requires-Dist: textual
